strictobject/__init__.py
strictobject/object.py
strictobject-0.0.1.dist-info/LICENSE
strictobject-0.0.1.dist-info/METADATA
strictobject-0.0.1.dist-info/WHEEL
strictobject-0.0.1.dist-info/top_level.txt
strictobject-0.0.1.dist-info/RECORD
