Metadata-Version: 2.1
Name: strictobject
Version: 0.0.1
Summary: Lightweight validation for python objects.
Author: leonixyz
Project-URL: Homepage, https://github.com/leonixyz/strictobject
Project-URL: Bug Tracker, https://github.com/leonixyz/strictobject/issues
Classifier: Programming Language :: Python :: 3
Classifier: License :: OSI Approved :: GNU Lesser General Public License v2 or later (LGPLv2+)
Classifier: Operating System :: OS Independent
Requires-Python: >=3.7
License-File: LICENSE
